lazgi/__init__.py
lazgi/_types.py
lazgi/py.typed
lazgi-0.1.0.dist-info/METADATA
lazgi-0.1.0.dist-info/WHEEL
lazgi-0.1.0.dist-info/licenses/LICENSE.txt
lazgi-0.1.0.dist-info/RECORD
