Metadata-Version: 2.4
Name: lazgi
Version: 0.1.0
Summary: Lazily created ASGI apps
Project-URL: Repository, https://github.com/adriangb/lazgi
Project-URL: Documentation, https://github.com/adriangb/lazgi
Author-email: Adrian Garcia Badaracco <adrian@adriangb.com>
License-Expression: MIT
License-File: LICENSE.txt
Keywords: asgi,http,web-framework
Classifier: Development Status :: 3 - Alpha
Classifier: Environment :: Web Environment
Classifier: Framework :: AsyncIO
Classifier: Intended Audience :: Developers
Classifier: Intended Audience :: Information Technology
Classifier: Intended Audience :: System Administrators
Classifier: License :: OSI Approved :: MIT License
Classifier: Operating System :: OS Independent
Classifier: Programming Language :: Python
Classifier: Programming Language :: Python :: 3
Classifier: Programming Language :: Python :: 3 :: Only
Classifier: Programming Language :: Python :: 3.7
Classifier: Programming Language :: Python :: 3.8
Classifier: Programming Language :: Python :: 3.9
Classifier: Programming Language :: Python :: 3.10
Classifier: Topic :: Internet
Classifier: Topic :: Internet :: WWW/HTTP
Classifier: Topic :: Internet :: WWW/HTTP :: HTTP Servers
Classifier: Topic :: Software Development
Classifier: Topic :: Software Development :: Libraries
Classifier: Topic :: Software Development :: Libraries :: Application Frameworks
Classifier: Topic :: Software Development :: Libraries :: Python Modules
Classifier: Typing :: Typed
Requires-Python: <4,>=3.7
Requires-Dist: asgi-lifespan-middleware>=0.1.3
